LICENSE
__init__.py
pyeldriver.py
pyeldriver-0.1.0.dist-info/LICENSE
pyeldriver-0.1.0.dist-info/WHEEL
pyeldriver-0.1.0.dist-info/METADATA
pyeldriver-0.1.0.dist-info/RECORD
