Metadata-Version: 2.1
Name: pyeldriver
Version: 0.1.0
Summary: Python function -> HTML string utility.
Home-page: https://github.com/telboyWA/pyel-driver
License: MIT
Author: telboyWA
Author-email: telstupple@gmail.com
Requires-Python: >=3.9,<4.0
Classifier: License :: OSI Approved :: MIT License
Classifier: Operating System :: OS Independent
Classifier: Programming Language :: Python :: 3
Classifier: Programming Language :: Python :: 3.9
Project-URL: Repository, https://github.com/telboyWA/pyel-driver
